{"is_source_file": true, "format": "JavaScript (React JSX)", "description": "This file defines a React functional component named Progress that renders a placeholder page for progress tracking.", "external_files": ["react"], "external_methods": [], "published": ["Progress"], "classes": [], "methods": [{"name": "Progress()", "description": "React functional component rendering a progress tracking page placeholder.", "scope": "", "scopeKind": ""}], "calls": [], "search-terms": ["Progress.jsx", "React component", "Progress page", "Progress placeholder"], "state": 2, "file_id": 24, "knowledge_revision": 48, "git_revision": "", "ctags": [{"_type": "tag", "name": "Progress", "path": "/home/kavia/workspace/code-generation/manga-and-anime-tracker-40879-40888/koma_corner_frontend/src/pages/Progress.jsx", "pattern": "/^export default function Progress() {$/", "language": "JavaScript", "kind": "function", "signature": "()"}], "hash": "52be274fe85c0655450a9b88460a872d", "format-version": 4, "code-base-name": "koma_corner_frontend", "filename": "koma_corner_frontend/src/pages/Progress.jsx", "revision_history": [{"48": ""}]}