{"is_source_file": true, "format": "JavaScript/React JSX", "description": "This is a React component for the home page of a media tracking application. It fetches and displays trending anime media items using react-query and a custom GraphQL request function.", "external_files": ["../lib/anilistClient", "../api/anilistQueries", "../components/MediaCard"], "external_methods": ["gqlRequest", "useQuery"], "published": [], "classes": [], "methods": [{"name": "Home()", "description": "React functional component that fetches and displays trending media items.", "scope": "", "scopeKind": ""}], "calls": ["useQuery", "gqlRequest", "MediaCard"], "search-terms": ["Home.jsx", "Trending Media", "React Query", "GraphQL", "MediaCard", "Anime", "Trending"], "state": 2, "file_id": 21, "knowledge_revision": 42, "git_revision": "", "ctags": [{"_type": "tag", "name": "Home", "path": "/home/kavia/workspace/code-generation/manga-and-anime-tracker-40879-40888/koma_corner_frontend/src/pages/Home.jsx", "pattern": "/^export default function Home() {$/", "language": "JavaScript", "kind": "function", "signature": "()"}], "hash": "2d7ffb763523c45d05d79a8995671f3b", "format-version": 4, "code-base-name": "koma_corner_frontend", "filename": "koma_corner_frontend/src/pages/Home.jsx", "revision_history": [{"42": ""}]}